{"d":"2026-05-06","sid":"d1e959426e57","m":[["inshop_24513","Бефстроганов из говядины с картофельным пюре",272.0,"vv:site_thumb/1a5dddea-9e38-47c1-a508-36740cf7619b.jpg",null,"unknown",""],["inshop_39535","Чиабатта с курицей, 205 г",224.0,"vv:site_thumb/56544aab-db77-46c8-9d28-77093575588b.jpg",null,"unknown",""],["inshop_50389","Ролл \"Симфония классики\" с креветкой",296.0,"vv:site/site_thumb/df3d6adc-2e10-4199-8eec-c3dc31765f5c.jpg",null,"unknown",""],["inshop_51256","Творог 5% 200 г",114.0,"vv:site_thumb/47889693-6e2a-4b25-8cc0-0baf12d9a924.jpg",null,"unknown",""],["inshop_82086","Суп \"Уха\" (с горбушей, судаком, палтусом), 270 г",208.0,"vv:site/site_thumb/daf7a1c6-7680-4a82-8b53-3af78fc17d27.jpg",null,"unknown",""],["inshop_112920","Салат \"Зеленый\" с брынзой, эдамаме и медово-горчичным соусом, 450 г",440.0,"vv:site/site_thumb/74c196aa-cfc4-4c56-a082-e3e619859412.jpg",null,"unknown",""],["inshop_22929","Куриное филе запеченное с овощами",272.0,"vv:site_thumb/61ed079d-eded-4190-a619-2f2e19990cfd.jpg",null,"unknown",""],["inshop_25290","Салат \"Оливье\", 150 г",160.0,"vv:site/site_thumb/48d357a4-fb52-41fd-9b4f-4db93a6dfe35.jpg",null,"unknown",""],["inshop_39387","Напиток клубничный с базиликом, 1 л",166.0,"vv:site/site_thumb/38e19b67-14ec-4c76-9660-af2cea120ba3.jpg",null,"unknown",""],["inshop_56109","Йогурт \"Персик-маракуйя\" высокобелковый 1,7%",68.0,"vv:site/site_thumb/16395fab-5d3f-4363-80fe-4ea7c29d0be7.jpg",null,"unknown",""],["inshop_92847","Клаб-сэндвич с куриным пате и копчено-вареным беконом",192.0,"vv:site_thumb/447edd7b-6af9-40a4-b8a2-680591e0adc5.jpg",null,"unknown",""],["inshop_109653","Напиток \"Шорли\" яблочный с грушей, 500 мл",116.0,"vv:site/site_thumb/3a44fc50-1e48-43ca-a57a-0aafdb29f89a.jpg",null,"unknown",""],["inshop_16417","Суп \"Гороховый\" с копчёностями",198.0,"vv:site/site_thumb/3f70dc44-2c51-44d5-bb69-7e2ec23585c3.jpg",null,"unknown",""],["inshop_51436","Сыр \"Маасдам\" нарезка, 150г",210.0,"vv:site_thumb/020a47fb-37d0-41d8-a0e2-4e0c44a60aad.jpg",null,"unknown",""],["inshop_52746","Напиток \"Гранат\" безалкогольный газированный, 330 мл",94.0,"vv:site/site_thumb/8d50abbe-1e30-424a-8fab-224492ad28eb.jpg",null,"unknown",""],["inshop_63729","Шаурма с курицей и печеным картофелем",248.0,"vv:site_thumb/47696f8d-b52b-4bd3-800e-5e302a255bf3.jpg",null,"unknown",""],["inshop_71621","Картофель запеченный с ветчиной куриной под сыром",256.0,"vv:site_thumb/1ee5470b-3579-4ec7-9e8d-c17ab96101d7.jpg",null,"unknown",""],["inshop_108186","Салат с консервированным тунцом и яблоком",230.0,"vv:site_thumb/525e927d-90cd-400b-a775-098e467b32d0.jpg",null,"unknown",""],["inshop_90844","Тунец (скипджек) филе в масле, 140 г",148.0,"https://vkusvill.ru/local/templates/main-responsive/img/vv22_app_banner/icon-appstore.svg",null,"unknown",""]],"g":[[0,1,2,3,4,5],[6,7,8,9,10,11],[12,13,14,15,16,17]],"f":[18],"r":[],"gt":[],"rc":18,"cap":18,"rs":{"k":"idle","t":"Можно редактировать","s":"Новый раунд готов. Можно выбирать товары.","b":"Открыто"},"round_status":{"k":"idle","t":"Можно редактировать","s":"Новый раунд готов. Можно выбирать товары.","b":"Открыто"},"im":{"inshop_39387":"img-cache/current/inshop_39387.webp","inshop_63729":"img-cache/current/inshop_63729.webp"},"generated_at":"2026-05-06T09:00:47+03:00"}